MANIFEST.in
TODO
ez_setup.py
makefile
setup.cfg
setup.py
bin/pudge
bin/pudge_devel.py
doc/index.rst
pudge/__init__.py
pudge/browser.py
pudge/cli.py
pudge/colorizer.py
pudge/dpcodeblocksupport.py
pudge/generator.py
pudge/peruser.py
pudge/pygmentsupport.py
pudge/rst.py
pudge/scanner.py
pudge.egg-info/PKG-INFO
pudge.egg-info/SOURCES.txt
pudge.egg-info/dependency_links.txt
pudge.egg-info/requires.txt
pudge.egg-info/top_level.txt
pudge/licenses/cc.rst
pudge/licenses/gnu.rst
pudge/template/base/class.html
pudge/template/base/common.html
pudge/template/base/document.html
pudge/template/base/layout.css
pudge/template/base/layout.html
pudge/template/base/master-index.html
pudge/template/base/member.html
pudge/template/base/module-index.html
pudge/template/base/module.html
pudge/template/base/package-index.html
pudge/template/base/pudge.css
pudge/template/base/rst.css
pudge/template/base/transitions.html
pudge/template/green/layout.css
pudge/template/green/layout.html
pudge/template/lesscode.org/almodovar.css
pudge/template/lesscode.org/layout.css
pudge/template/lesscode.org/layout.html
pudge/template/orbtech.com/custom.css
pudge/template/orbtech.com/layout.css
pudge/template/orbtech.com/layout.html
pudge/template/orbtech.com/screen.css
pudge/template/orbtech.com/silvercity.css
pudge/template/orbtech.com/1st/1st.txt
pudge/template/orbtech.com/1st/menu.py
pudge/template/pythonpaste.org/layout.css
pudge/template/pythonpaste.org/layout.html
pudge/template/pythonpaste.org/pudge.css
pudge/template/pythonpaste.org/rst.css
pudge/template/pythonpaste.org/site.css.kid
pudge/test/__init__.py
pudge/test/conftest.py
pudge/test/setupenv.py
pudge/test/test_browser.py
pudge/test/test_cli.py
pudge/test/test_colorizer.py
pudge/test/test_generator.py
pudge/test/test_package.py
pudge/test/test_peruser.py
pudge/test/test_rst.py
pudge/test/test_scanner.py
pudge/test/data/medium.py
pudge/test/data/short.py
pudge/test/package/__init__.py
pudge/test/package/subpackage/__init__.py
