Metadata-Version: 1.0
Name: pudge
Version: 0.1.3
Summary: Pudge is a documentation generator for Python projects, using Restructured Text
Home-page: http://lesscode.org/projects/pudge/
Author: Ryan Tomayko
Author-email: rtomayko@gmail.com
License: MIT
Keywords: documentation doc html
Platform: any
Classifier: Development Status :: 3 - Alpha
Classifier: Environment :: Console
Classifier: Environment :: Web Environment
Classifier: Intended Audience :: Developers
Classifier: License :: OSI Approved :: MIT License
Classifier: Operating System :: OS Independent
Classifier: Programming Language :: Python
Classifier: Topic :: Internet :: WWW/HTTP
Classifier: Topic :: Software Development :: Libraries :: Python Modules
